hl7tojson/__init__.py
hl7tojson/fields.pickle
hl7tojson/messages.pickle
hl7tojson/parser.py
hl7tojson/segments.pickle
hl7tojson/data/__init__.py
hl7tojson/data/27/__init__.py
hl7tojson/data/27/fields.json
hl7tojson/data/27/fields.pickle
hl7tojson/data/27/messages.json
hl7tojson/data/27/messages.pickle
hl7tojson/data/27/segments.json
hl7tojson/data/27/segments.pickle
tests/__init__.py
tests/samples.py
tests/test_parser.py
hl7tojson-0.0.2.dist-info/LICENSE
hl7tojson-0.0.2.dist-info/METADATA
hl7tojson-0.0.2.dist-info/WHEEL
hl7tojson-0.0.2.dist-info/top_level.txt
hl7tojson-0.0.2.dist-info/RECORD
