Metadata-Version: 2.1
Name: hl7tojson
Version: 0.0.2
Summary: A simple library to convert HL7 message version 2 to JSON with human readable description
Home-page: https://github.com/jerry-le/hl7tojson
Author: Jerry Le
Author-email: khanh96le@gmail.com
License: UNKNOWN
Keywords: HL7,Health Level 7,healthcare,health care,medical record
Platform: UNKNOWN
Classifier: Programming Language :: Python :: 2
Classifier: License :: OSI Approved :: MIT License
Classifier: Operating System :: OS Independent
Requires-Dist: hl7 (==0.3.4)
Requires-Dist: six (==1.11.0)
